ti842py/__init__.py
ti842py/__version__.py
ti842py/main.py
ti842py/parsing_utils.py
ti842py/ti_parser.py
ti842py/token_utils.py
ti842py/utils/clear.py
ti842py/utils/draw.py
ti842py/utils/fix_floating_point.py
ti842py/utils/get_datetime.py
ti842py/utils/getkey.py
ti842py/utils/goto.py
ti842py/utils/matrix.py
ti842py/utils/output.py
ti842py/utils/prgm.py
ti842py/utils/round.py
ti842py/utils/to_number.py
ti842py-0.9.10.dist-info/LICENSE
ti842py-0.9.10.dist-info/METADATA
ti842py-0.9.10.dist-info/WHEEL
ti842py-0.9.10.dist-info/entry_points.txt
ti842py-0.9.10.dist-info/top_level.txt
ti842py-0.9.10.dist-info/RECORD
