Metadata-Version: 2.1
Name: ti842py
Version: 0.9.10
Summary: TI-BASIC to Python 3 Transpiler
Home-page: https://github.com/TabulateJarl8/ti842py
Author: Tabulate
Author-email: tabulatejarl8@gmail.com
License: UNKNOWN
Platform: UNKNOWN
Classifier: Programming Language :: Python :: 3
Classifier: License :: OSI Approved :: GNU General Public License v3 (GPLv3)
Classifier: Operating System :: OS Independent
Classifier: Operating System :: POSIX :: Linux
Classifier: Environment :: Console
Classifier: Development Status :: 4 - Beta
Classifier: Intended Audience :: End Users/Desktop
Classifier: Intended Audience :: Developers
Requires-Python: >=3.6
License-File: LICENSE
Requires-Dist: basically-ti-basic (>=0.1.6)
Requires-Dist: pythondialog (>=3.5.1)
Requires-Dist: graphics.py (>=5.0.0)
Requires-Dist: pynput (>=1.7.3)
